Metadata-Version: 2.1
Name: PanaceaMobile
Version: 1.0.2
Summary: PanaceaMobile "API" implementation in Python
Home-page: https://gitlab.com/jargij/panaceamobile-python
Author: Jacek Smit
Author-email: info@jaceksmit.nl
License: MIT
Keywords: SMS,PanaceaMobile,messaging
Platform: any
Classifier: Development Status :: 5 - Production/Stable
Classifier: Environment :: Console
Classifier: Intended Audience :: Developers
Classifier: Intended Audience :: Telecommunications Industry
Classifier: Topic :: Communications :: Telephony
Classifier: License :: OSI Approved :: MIT License
Classifier: Programming Language :: Python :: 3
Requires-Python: >=3.5
